{
  "layout": "banner_icon",
  "contents": {
    "title": "NUOVA <b>OFFERTA<\/b>",
    "cta": {
      "title": "Scopri l' offerta",
      "url": "#",
      "target": ""
    },
    "cta_2_cta": {
      "title": "Scopri l' offerta",
      "url": "#",
      "target": ""
    },
    "description": "Lorem ipsum dolor sit amet, consectetuer adipiscing elit. Consectetuer adipiscing elit. Aenean commodo ligula eget dolor.Aenean commodo ligula eget dolor. Lorem ipsum dolor sit amet, consectetuer adipiscing elit. consectetuer adipiscing elit. Aenean commodo ligula eget dolor. Aenean commodo ligula eget dolor..",
    "icon_image": {
      "ID": 2231,
      "id": 2231,
      "title": "banner_icon",
      "filename": "banner_icon.png",
      "filesize": 2240,
      "url": "http:\/\/localhost\/wp-content\/uploads\/2018\/05\/banner_icon.png",
      "link": "http:\/\/localhost\/negozi-e-uffici\/banner_icon\/",
      "alt": "",
      "author": "1",
      "description": "",
      "caption": "",
      "name": "banner_icon",
      "status": "inherit",
      "uploaded_to": 915,
      "date": "2018-05-06 13:53:09",
      "modified": "2018-05-06 13:53:09",
      "menu_order": 0,
      "mime_type": "image\/png",
      "type": "image",
      "subtype": "png",
      "icon": "http:\/\/localhost\/wp-includes\/images\/media\/default.png",
      "width": 49,
      "height": 43,
      "sizes": {
        "thumbnail": "http:\/\/localhost\/wp-content\/uploads\/2018\/05\/banner_icon.png",
        "thumbnail-width": 49,
        "thumbnail-height": 43,
        "medium": "http:\/\/localhost\/wp-content\/uploads\/2018\/05\/banner_icon.png",
        "medium-width": 49,
        "medium-height": 43,
        "medium_large": "http:\/\/localhost\/wp-content\/uploads\/2018\/05\/banner_icon.png",
        "medium_large-width": 49,
        "medium_large-height": 43,
        "large": "http:\/\/localhost\/wp-content\/uploads\/2018\/05\/banner_icon.png",
        "large-width": 49,
        "large-height": 43
      }
    }
  }
}
